bluer_options/__init__.py
bluer_options/__main__.py
bluer_options/config.env
bluer_options/testing.py
bluer_options/timer.py
bluer_options/urls.py
bluer_options/.bash/alias.sh
bluer_options/.bash/assert.sh
bluer_options/.bash/bluer_options.sh
bluer_options/.bash/bool.sh
bluer_options/.bash/browse.sh
bluer_options/.bash/code.sh
bluer_options/.bash/env.sh
bluer_options/.bash/eval.sh
bluer_options/.bash/generic_task.sh
bluer_options/.bash/help.sh
bluer_options/.bash/install.sh
bluer_options/.bash/list.sh
bluer_options/.bash/logging.sh
bluer_options/.bash/open.sh
bluer_options/.bash/options.sh
bluer_options/.bash/pause.sh
bluer_options/.bash/plugins.sh
bluer_options/.bash/pylint.sh
bluer_options/.bash/pytest.sh
bluer_options/.bash/repeat.sh
bluer_options/.bash/seed.sh
bluer_options/.bash/sleep.sh
bluer_options/.bash/source.sh
bluer_options/.bash/string.sh
bluer_options/.bash/terminal.sh
bluer_options/.bash/test.sh
bluer_options/.bash/wait.sh
bluer_options/.bash/watch.sh
bluer_options/.bash/env/backup.sh
bluer_options/.bash/env/dot.sh
bluer_options/.bash/env/dot/cat.sh
bluer_options/.bash/env/dot/cp.sh
bluer_options/.bash/env/dot/edit.sh
bluer_options/.bash/env/dot/load.sh
bluer_options/.bash/env/dot/seed.sh
bluer_options/assets/example1.sh
bluer_options/env/__init__.py
bluer_options/env/functions.py
bluer_options/help/__init__.py
bluer_options/help/__main__.py
bluer_options/help/functions.py
bluer_options/help/parsing.py
bluer_options/host/__init__.py
bluer_options/host/__main__.py
bluer_options/host/functions.py
bluer_options/list/__init__.py
bluer_options/list/__main__.py
bluer_options/logger/__init__.py
bluer_options/logger/__main__.py
bluer_options/logger/config.py
bluer_options/logger/watch.py
bluer_options/options/__init__.py
bluer_options/options/__main__.py
bluer_options/options/classes.py
bluer_options/string/__init__.py
bluer_options/string/__main__.py
bluer_options/string/constants.py
bluer_options/string/functions.py
bluer_options/terminal/__init__.py
bluer_options-5.296.1.dist-info/licenses/LICENSE
bluer_options-5.296.1.dist-info/METADATA
bluer_options-5.296.1.dist-info/WHEEL
bluer_options-5.296.1.dist-info/top_level.txt
bluer_options-5.296.1.dist-info/RECORD
