Metadata-Version: 2.4
Name: bluer_options
Version: 5.296.1
Summary: 🌀 Options for Bash.
Home-page: https://github.com/kamangir/bluer-options
Author: Arash Abadpour (Kamangir)
Author-email: arash.abadpour@gmail.com
License: CC0-1.0
Classifier: Programming Language :: Python :: 3
Classifier: Programming Language :: Unix Shell
Classifier: Operating System :: OS Independent
License-File: LICENSE
Requires-Dist: blueness
Requires-Dist: matplotlib
Requires-Dist: numpy
Requires-Dist: pymysql
Requires-Dist: python-dotenv[cli]
Dynamic: author
Dynamic: author-email
Dynamic: classifier
Dynamic: description
Dynamic: description-content-type
Dynamic: home-page
Dynamic: license
Dynamic: license-file
Dynamic: requires-dist
Dynamic: summary
